{
  "meta": {
    "file": "hinase/hinase_2.txt",
    "chapter": "hinase",
    "total_lines": 73,
    "generated_at": "2026-04-23",
    "version": "v0.1.0"
  },
  "entries": [
    {
      "line": 1,
      "jp": "日生先輩はいつでも余裕だ。",
      "cn": "",
      "type": "narration",
      "translations": {
        "v1": "",
        "v2": "",
        "v3": "",
        "final": ""
      },
      "verified": false,
      "context": {
        "before": null,
        "after": "こちらも余裕な振りをしてみるけれど、全て見透かされてしまう。"
      }
    },
    {
      "line": 2,
      "jp": "こちらも余裕な振りをしてみるけれど、全て見透かされてしまう。",
      "cn": "",
      "type": "narration",
      "translations": {
        "v1": "",
        "v2": "",
        "v3": "",
        "final": ""
      },
      "verified": false,
      "context": {
        "before": "日生先輩はいつでも余裕だ。",
        "after": "だからこそ、日生先輩の隣は居心地が良い。"
      }
    },
    {
      "line": 3,
      "jp": "だからこそ、日生先輩の隣は居心地が良い。",
      "cn": "",
      "type": "narration",
      "translations": {
        "v1": "",
        "v2": "",
        "v3": "",
        "final": ""
      },
      "verified": false,
      "context": {
        "before": "こちらも余裕な振りをしてみるけれど、全て見透かされてしまう。",
        "after": "何も言わなくても分かってくれる。"
      }
    },
    {
      "line": 4,
      "jp": "何も言わなくても分かってくれる。",
      "cn": "",
      "type": "narration",
      "translations": {
        "v1": "",
        "v2": "",
        "v3": "",
        "final": ""
      },
      "verified": false,
      "context": {
        "before": "だからこそ、日生先輩の隣は居心地が良い。",
        "after": "私の欲しい言葉をくれる。"
      }
    },
    {
      "line": 5,
      "jp": "私の欲しい言葉をくれる。",
      "cn": "",
      "type": "narration",
      "translations": {
        "v1": "",
        "v2": "",
        "v3": "",
        "final": ""
      },
      "verified": false,
      "context": {
        "before": "何も言わなくても分かってくれる。",
        "after": "嫌いじゃないから付き合って、付き合ったからこんなことをしている。"
      }
    },
    {
      "line": 6,
      "jp": "嫌いじゃないから付き合って、付き合ったからこんなことをしている。",
      "cn": "",
      "type": "narration",
      "translations": {
        "v1": "",
        "v2": "",
        "v3": "",
        "final": ""
      },
      "verified": false,
      "context": {
        "before": "私の欲しい言葉をくれる。",
        "after": "間違っているのだろうか？"
      }
    },
    {
      "line": 7,
      "jp": "間違っているのだろうか？",
      "cn": "",
      "type": "narration",
      "translations": {
        "v1": "",
        "v2": "",
        "v3": "",
        "final": ""
      },
      "verified": false,
      "context": {
        "before": "嫌いじゃないから付き合って、付き合ったからこんなことをしている。",
        "after": "けれど……"
      }
    },
    {
      "line": 8,
      "jp": "けれど……",
      "cn": "",
      "type": "narration",
      "translations": {
        "v1": "",
        "v2": "",
        "v3": "",
        "final": ""
      },
      "verified": false,
      "context": {
        "before": "間違っているのだろうか？",
        "after": "遠野　紗夜「…………」"
      }
    },
    {
      "line": 9,
      "jp": "遠野　紗夜「…………」",
      "cn": "",
      "type": "dialogue",
      "translations": {
        "v1": "",
        "v2": "",
        "v3": "",
        "final": ""
      },
      "verified": false,
      "speaker": "遠野　紗夜",
      "special_char": true,
      "context": {
        "before": "けれど……",
        "after": "遠野　紗夜「……先輩、遅いですね」"
      }
    },
    {
      "line": 10,
      "jp": "遠野　紗夜「……先輩、遅いですね」",
      "cn": "",
      "type": "dialogue",
      "translations": {
        "v1": "",
        "v2": "",
        "v3": "",
        "final": ""
      },
      "verified": false,
      "speaker": "遠野　紗夜",
      "special_char": true,
      "context": {
        "before": "遠野　紗夜「…………」",
        "after": "体を起こし、床に無造作に落ちたジャケットを手に取る。"
      }
    },
    {
      "line": 11,
      "jp": "体を起こし、床に無造作に落ちたジャケットを手に取る。",
      "cn": "",
      "type": "narration",
      "translations": {
        "v1": "",
        "v2": "",
        "v3": "",
        "final": ""
      },
      "verified": false,
      "context": {
        "before": "遠野　紗夜「……先輩、遅いですね」",
        "after": "ドアノブに手をかけようとした、その瞬間。"
      }
    },
    {
      "line": 12,
      "jp": "ドアノブに手をかけようとした、その瞬間。",
      "cn": "",
      "type": "narration",
      "translations": {
        "v1": "",
        "v2": "",
        "v3": "",
        "final": ""
      },
      "verified": false,
      "context": {
        "before": "体を起こし、床に無造作に落ちたジャケットを手に取る。",
        "after": "？？？「光さん」"
      }
    },
    {
      "line": 13,
      "jp": "？？？「光さん」",
      "cn": "",
      "type": "dialogue",
      "translations": {
        "v1": "",
        "v2": "",
        "v3": "",
        "final": ""
      },
      "verified": false,
      "speaker": "？？？",
      "special_char": true,
      "context": {
        "before": "ドアノブに手をかけようとした、その瞬間。",
        "after": "私の知らない声が聞こえた。"
      }
    },
    {
      "line": 14,
      "jp": "私の知らない声が聞こえた。",
      "cn": "",
      "type": "narration",
      "translations": {
        "v1": "",
        "v2": "",
        "v3": "",
        "final": ""
      },
      "verified": false,
      "context": {
        "before": "？？？「光さん」",
        "after": "落ち着いた深みのある女性の声。"
      }
    },
    {
      "line": 15,
      "jp": "落ち着いた深みのある女性の声。",
      "cn": "",
      "type": "narration",
      "translations": {
        "v1": "",
        "v2": "",
        "v3": "",
        "final": ""
      },
      "verified": false,
      "context": {
        "before": "私の知らない声が聞こえた。",
        "after": "日生　光「今日は随分と早いお帰りなんですね。お祖母様」"
      }
    },
    {
      "line": 16,
      "jp": "日生　光「今日は随分と早いお帰りなんですね。お祖母様」",
      "cn": "",
      "type": "dialogue",
      "translations": {
        "v1": "",
        "v2": "",
        "v3": "",
        "final": ""
      },
      "verified": false,
      "speaker": "日生　光",
      "special_char": true,
      "context": {
        "before": "落ち着いた深みのある女性の声。",
        "after": "日生先輩の声がする。"
      }
    },
    {
      "line": 17,
      "jp": "日生先輩の声がする。",
      "cn": "",
      "type": "narration",
      "translations": {
        "v1": "",
        "v2": "",
        "v3": "",
        "final": ""
      },
      "verified": false,
      "context": {
        "before": "日生　光「今日は随分と早いお帰りなんですね。お祖母様」",
        "after": "その言葉から、先程の女性は彼の『お祖母様』だということは分かった。"
      }
    },
    {
      "line": 18,
      "jp": "その言葉から、先程の女性は彼の『お祖母様』だということは分かった。",
      "cn": "",
      "type": "narration",
      "translations": {
        "v1": "",
        "v2": "",
        "v3": "",
        "final": ""
      },
      "verified": false,
      "context": {
        "before": "日生先輩の声がする。",
        "after": "日生祖母「ええ。……その手に持っているのは何です？」"
      }
    },
    {
      "line": 19,
      "jp": "日生祖母「ええ。……その手に持っているのは何です？」",
      "cn": "",
      "type": "dialogue",
      "translations": {
        "v1": "",
        "v2": "",
        "v3": "",
        "final": ""
      },
      "verified": false,
      "speaker": "日生祖母",
      "special_char": true,
      "context": {
        "before": "その言葉から、先程の女性は彼の『お祖母様』だということは分かった。",
        "after": "日生　光「これ？　ただの砂糖ですよ」"
      }
    },
    {
      "line": 20,
      "jp": "日生　光「これ？　ただの砂糖ですよ」",
      "cn": "",
      "type": "dialogue",
      "translations": {
        "v1": "",
        "v2": "",
        "v3": "",
        "final": ""
      },
      "verified": false,
      "speaker": "日生　光",
      "special_char": true,
      "context": {
        "before": "日生祖母「ええ。……その手に持っているのは何です？」",
        "after": "日生祖母「砂糖？　貴方が？」"
      }
    },
    {
      "line": 21,
      "jp": "日生祖母「砂糖？　貴方が？」",
      "cn": "",
      "type": "dialogue",
      "translations": {
        "v1": "",
        "v2": "",
        "v3": "",
        "final": ""
      },
      "verified": false,
      "speaker": "日生祖母",
      "special_char": true,
      "context": {
        "before": "日生　光「これ？　ただの砂糖ですよ」",
        "after": "日生　光「おかしいですか？」"
      }
    },
    {
      "line": 22,
      "jp": "日生　光「おかしいですか？」",
      "cn": "",
      "type": "dialogue",
      "translations": {
        "v1": "",
        "v2": "",
        "v3": "",
        "final": ""
      },
      "verified": false,
      "speaker": "日生　光",
      "special_char": true,
      "context": {
        "before": "日生祖母「砂糖？　貴方が？」",
        "after": "日生祖母「……誰か来ているのですか？」"
      }
    },
    {
      "line": 23,
      "jp": "日生祖母「……誰か来ているのですか？」",
      "cn": "",
      "type": "dialogue",
      "translations": {
        "v1": "",
        "v2": "",
        "v3": "",
        "final": ""
      },
      "verified": false,
      "speaker": "日生祖母",
      "special_char": true,
      "context": {
        "before": "日生　光「おかしいですか？」",
        "after": "日生　光「いいえ」"
      }
    },
    {
      "line": 24,
      "jp": "日生　光「いいえ」",
      "cn": "",
      "type": "dialogue",
      "translations": {
        "v1": "",
        "v2": "",
        "v3": "",
        "final": ""
      },
      "verified": false,
      "speaker": "日生　光",
      "special_char": true,
      "context": {
        "before": "日生祖母「……誰か来ているのですか？」",
        "after": "遠野　紗夜「……っ」"
      }
    },
    {
      "line": 25,
      "jp": "遠野　紗夜「……っ」",
      "cn": "",
      "type": "dialogue",
      "translations": {
        "v1": "",
        "v2": "",
        "v3": "",
        "final": ""
      },
      "verified": false,
      "speaker": "遠野　紗夜",
      "special_char": true,
      "context": {
        "before": "日生　光「いいえ」",
        "after": "私は急いで部屋を見渡す。"
      }
    },
    {
      "line": 26,
      "jp": "私は急いで部屋を見渡す。",
      "cn": "",
      "type": "narration",
      "translations": {
        "v1": "",
        "v2": "",
        "v3": "",
        "final": ""
      },
      "verified": false,
      "context": {
        "before": "遠野　紗夜「……っ」",
        "after": "目についたのはアンティーク調のクローゼットだった。"
      }
    },
    {
      "line": 27,
      "jp": "目についたのはアンティーク調のクローゼットだった。",
      "cn": "",
      "type": "narration",
      "translations": {
        "v1": "",
        "v2": "",
        "v3": "",
        "final": ""
      },
      "verified": false,
      "context": {
        "before": "私は急いで部屋を見渡す。",
        "after": "日生祖母「…………」"
      }
    },
    {
      "line": 28,
      "jp": "日生祖母「…………」",
      "cn": "",
      "type": "dialogue",
      "translations": {
        "v1": "",
        "v2": "",
        "v3": "",
        "final": ""
      },
      "verified": false,
      "speaker": "日生祖母",
      "special_char": true,
      "context": {
        "before": "目についたのはアンティーク調のクローゼットだった。",
        "after": "日生　光「……ね？　だから言ったでしょう？　誰もいないって」"
      }
    },
    {
      "line": 29,
      "jp": "日生　光「……ね？　だから言ったでしょう？　誰もいないって」",
      "cn": "",
      "type": "dialogue",
      "translations": {
        "v1": "",
        "v2": "",
        "v3": "",
        "final": ""
      },
      "verified": false,
      "speaker": "日生　光",
      "special_char": true,
      "context": {
        "before": "日生祖母「…………」",
        "after": "日生祖母「……そうですね」"
      }
    },
    {
      "line": 30,
      "jp": "日生祖母「……そうですね」",
      "cn": "",
      "type": "dialogue",
      "translations": {
        "v1": "",
        "v2": "",
        "v3": "",
        "final": ""
      },
      "verified": false,
      "speaker": "日生祖母",
      "special_char": true,
      "context": {
        "before": "日生　光「……ね？　だから言ったでしょう？　誰もいないって」",
        "after": "日生祖母「…………」"
      }
    },
    {
      "line": 31,
      "jp": "日生祖母「…………」",
      "cn": "",
      "type": "dialogue",
      "translations": {
        "v1": "",
        "v2": "",
        "v3": "",
        "final": ""
      },
      "verified": false,
      "speaker": "日生祖母",
      "special_char": true,
      "context": {
        "before": "日生祖母「……そうですね」",
        "after": "日生祖母「……この香り、あまり品が良いと思えませんね」"
      }
    },
    {
      "line": 32,
      "jp": "日生祖母「……この香り、あまり品が良いと思えませんね」",
      "cn": "",
      "type": "dialogue",
      "translations": {
        "v1": "",
        "v2": "",
        "v3": "",
        "final": ""
      },
      "verified": false,
      "speaker": "日生祖母",
      "special_char": true,
      "context": {
        "before": "日生祖母「…………」",
        "after": "日生祖母「光さん」"
      }
    },
    {
      "line": 33,
      "jp": "日生祖母「光さん」",
      "cn": "",
      "type": "dialogue",
      "translations": {
        "v1": "",
        "v2": "",
        "v3": "",
        "final": ""
      },
      "verified": false,
      "speaker": "日生祖母",
      "special_char": true,
      "context": {
        "before": "日生祖母「……この香り、あまり品が良いと思えませんね」",
        "after": "日生祖母「貴方は日生の大事な後継者だということを努々忘れませんようにね」"
      }
    },
    {
      "line": 34,
      "jp": "日生祖母「貴方は日生の大事な後継者だということを努々忘れませんようにね」",
      "cn": "",
      "type": "dialogue",
      "translations": {
        "v1": "",
        "v2": "",
        "v3": "",
        "final": ""
      },
      "verified": false,
      "speaker": "日生祖母",
      "special_char": true,
      "context": {
        "before": "日生祖母「光さん」",
        "after": "日生　光「はい。お祖母様」"
      }
    },
    {
      "line": 35,
      "jp": "日生　光「はい。お祖母様」",
      "cn": "",
      "type": "dialogue",
      "translations": {
        "v1": "",
        "v2": "",
        "v3": "",
        "final": ""
      },
      "verified": false,
      "speaker": "日生　光",
      "special_char": true,
      "context": {
        "before": "日生祖母「貴方は日生の大事な後継者だということを努々忘れませんようにね」",
        "after": "日生　光「…………」"
      }
    },
    {
      "line": 36,
      "jp": "日生　光「…………」",
      "cn": "",
      "type": "dialogue",
      "translations": {
        "v1": "",
        "v2": "",
        "v3": "",
        "final": ""
      },
      "verified": false,
      "speaker": "日生　光",
      "special_char": true,
      "context": {
        "before": "日生　光「はい。お祖母様」",
        "after": "日生　光「……見ーつけた」"
      }
    },
    {
      "line": 37,
      "jp": "日生　光「……見ーつけた」",
      "cn": "",
      "type": "dialogue",
      "translations": {
        "v1": "",
        "v2": "",
        "v3": "",
        "final": ""
      },
      "verified": false,
      "speaker": "日生　光",
      "special_char": true,
      "context": {
        "before": "日生　光「…………」",
        "after": "暗闇から、日生先輩の顔が現れる。"
      }
    },
    {
      "line": 38,
      "jp": "暗闇から、日生先輩の顔が現れる。",
      "cn": "",
      "type": "narration",
      "translations": {
        "v1": "",
        "v2": "",
        "v3": "",
        "final": ""
      },
      "verified": false,
      "context": {
        "before": "日生　光「……見ーつけた」",
        "after": "一瞬の間だけだったけれど、それでも闇に馴れた眸に光はきつかった。"
      }
    },
    {
      "line": 39,
      "jp": "一瞬の間だけだったけれど、それでも闇に馴れた眸に光はきつかった。",
      "cn": "",
      "type": "narration",
      "translations": {
        "v1": "",
        "v2": "",
        "v3": "",
        "final": ""
      },
      "verified": false,
      "context": {
        "before": "暗闇から、日生先輩の顔が現れる。",
        "after": "私は目を細める。"
      }
    },
    {
      "line": 40,
      "jp": "私は目を細める。",
      "cn": "",
      "type": "narration",
      "translations": {
        "v1": "",
        "v2": "",
        "v3": "",
        "final": ""
      },
      "verified": false,
      "context": {
        "before": "一瞬の間だけだったけれど、それでも闇に馴れた眸に光はきつかった。",
        "after": "遠野　紗夜「…………」"
      }
    },
    {
      "line": 41,
      "jp": "遠野　紗夜「…………」",
      "cn": "",
      "type": "dialogue",
      "translations": {
        "v1": "",
        "v2": "",
        "v3": "",
        "final": ""
      },
      "verified": false,
      "speaker": "遠野　紗夜",
      "special_char": true,
      "context": {
        "before": "私は目を細める。",
        "after": "日生　光「流石だね。君のそういう聡いところ、好きだよ」"
      }
    },
    {
      "line": 42,
      "jp": "日生　光「流石だね。君のそういう聡いところ、好きだよ」",
      "cn": "",
      "type": "dialogue",
      "translations": {
        "v1": "",
        "v2": "",
        "v3": "",
        "final": ""
      },
      "verified": false,
      "speaker": "日生　光",
      "special_char": true,
      "context": {
        "before": "遠野　紗夜「…………」",
        "after": "遠野　紗夜「……今の方、先輩のお祖母様ですか？」"
      }
    },
    {
      "line": 43,
      "jp": "遠野　紗夜「……今の方、先輩のお祖母様ですか？」",
      "cn": "",
      "type": "dialogue",
      "translations": {
        "v1": "",
        "v2": "",
        "v3": "",
        "final": ""
      },
      "verified": false,
      "speaker": "遠野　紗夜",
      "special_char": true,
      "context": {
        "before": "日生　光「流石だね。君のそういう聡いところ、好きだよ」",
        "after": "日生　光「そう。とーっても厳しい、ね。君との関係がばれたら色々煩いだろうなぁ」"
      }
    },
    {
      "line": 44,
      "jp": "日生　光「そう。とーっても厳しい、ね。君との関係がばれたら色々煩いだろうなぁ」",
      "cn": "",
      "type": "dialogue",
      "translations": {
        "v1": "",
        "v2": "",
        "v3": "",
        "final": ""
      },
      "verified": false,
      "speaker": "日生　光",
      "special_char": true,
      "context": {
        "before": "遠野　紗夜「……今の方、先輩のお祖母様ですか？」",
        "after": "以前にも聞いたことがある。"
      }
    },
    {
      "line": 45,
      "jp": "以前にも聞いたことがある。",
      "cn": "",
      "type": "narration",
      "translations": {
        "v1": "",
        "v2": "",
        "v3": "",
        "final": ""
      },
      "verified": false,
      "context": {
        "before": "日生　光「そう。とーっても厳しい、ね。君との関係がばれたら色々煩いだろうなぁ」",
        "after": "日生先輩は家に帰る時間も気にしていた。"
      }
    },
    {
      "line": 46,
      "jp": "日生先輩は家に帰る時間も気にしていた。",
      "cn": "",
      "type": "narration",
      "translations": {
        "v1": "",
        "v2": "",
        "v3": "",
        "final": ""
      },
      "verified": false,
      "context": {
        "before": "以前にも聞いたことがある。",
        "after": "遠野　紗夜「私がいること、気付かれてしまったでしょうか？」"
      }
    },
    {
      "line": 47,
      "jp": "遠野　紗夜「私がいること、気付かれてしまったでしょうか？」",
      "cn": "",
      "type": "dialogue",
      "translations": {
        "v1": "",
        "v2": "",
        "v3": "",
        "final": ""
      },
      "verified": false,
      "speaker": "遠野　紗夜",
      "special_char": true,
      "context": {
        "before": "日生先輩は家に帰る時間も気にしていた。",
        "after": "日生　光「どうだろうね。まあ、もういないからこっちにおいで」"
      }
    },
    {
      "line": 48,
      "jp": "日生　光「どうだろうね。まあ、もういないからこっちにおいで」",
      "cn": "",
      "type": "dialogue",
      "translations": {
        "v1": "",
        "v2": "",
        "v3": "",
        "final": ""
      },
      "verified": false,
      "speaker": "日生　光",
      "special_char": true,
      "context": {
        "before": "遠野　紗夜「私がいること、気付かれてしまったでしょうか？」",
        "after": "差し出された手を取る。"
      }
    },
    {
      "line": 49,
      "jp": "差し出された手を取る。",
      "cn": "",
      "type": "narration",
      "translations": {
        "v1": "",
        "v2": "",
        "v3": "",
        "final": ""
      },
      "verified": false,
      "context": {
        "before": "日生　光「どうだろうね。まあ、もういないからこっちにおいで」",
        "after": "もう視界は元に戻った。"
      }
    },
    {
      "line": 50,
      "jp": "もう視界は元に戻った。",
      "cn": "",
      "type": "narration",
      "translations": {
        "v1": "",
        "v2": "",
        "v3": "",
        "final": ""
      },
      "verified": false,
      "context": {
        "before": "差し出された手を取る。",
        "after": "遠野　紗夜「…………」"
      }
    },
    {
      "line": 51,
      "jp": "遠野　紗夜「…………」",
      "cn": "",
      "type": "dialogue",
      "translations": {
        "v1": "",
        "v2": "",
        "v3": "",
        "final": ""
      },
      "verified": false,
      "speaker": "遠野　紗夜",
      "special_char": true,
      "context": {
        "before": "もう視界は元に戻った。",
        "after": "遠野　紗夜「……私、もう帰りますね。これ以上いると色々とご迷惑をおかけしてしまうかもしれませんし」"
      }
    },
    {
      "line": 52,
      "jp": "遠野　紗夜「……私、もう帰りますね。これ以上いると色々とご迷惑をおかけしてしまうかもしれませんし」",
      "cn": "",
      "type": "dialogue",
      "translations": {
        "v1": "",
        "v2": "",
        "v3": "",
        "final": ""
      },
      "verified": false,
      "speaker": "遠野　紗夜",
      "special_char": true,
      "context": {
        "before": "遠野　紗夜「…………」",
        "after": "日生　光「それは残念だなぁ。これからがお楽しみなのに」"
      }
    },
    {
      "line": 53,
      "jp": "日生　光「それは残念だなぁ。これからがお楽しみなのに」",
      "cn": "",
      "type": "dialogue",
      "translations": {
        "v1": "",
        "v2": "",
        "v3": "",
        "final": ""
      },
      "verified": false,
      "speaker": "日生　光",
      "special_char": true,
      "context": {
        "before": "遠野　紗夜「……私、もう帰りますね。これ以上いると色々とご迷惑をおかけしてしまうかもしれませんし」",
        "after": "日生先輩はからかう口調で言った後、ふうと息を吐いた。"
      }
    },
    {
      "line": 54,
      "jp": "日生先輩はからかう口調で言った後、ふうと息を吐いた。",
      "cn": "",
      "type": "narration",
      "translations": {
        "v1": "",
        "v2": "",
        "v3": "",
        "final": ""
      },
      "verified": false,
      "context": {
        "before": "日生　光「それは残念だなぁ。これからがお楽しみなのに」",
        "after": "日生　光「まあ、でも仕方ないか。何も今日だけが全てじゃないし」"
      }
    },
    {
      "line": 55,
      "jp": "日生　光「まあ、でも仕方ないか。何も今日だけが全てじゃないし」",
      "cn": "",
      "type": "dialogue",
      "translations": {
        "v1": "",
        "v2": "",
        "v3": "",
        "final": ""
      },
      "verified": false,
      "speaker": "日生　光",
      "special_char": true,
      "context": {
        "before": "日生先輩はからかう口調で言った後、ふうと息を吐いた。",
        "after": "遠野　紗夜「ええ」"
      }
    },
    {
      "line": 56,
      "jp": "遠野　紗夜「ええ」",
      "cn": "",
      "type": "dialogue",
      "translations": {
        "v1": "",
        "v2": "",
        "v3": "",
        "final": ""
      },
      "verified": false,
      "speaker": "遠野　紗夜",
      "special_char": true,
      "context": {
        "before": "日生　光「まあ、でも仕方ないか。何も今日だけが全てじゃないし」",
        "after": "私は窓枠に手をかける。"
      }
    },
    {
      "line": 57,
      "jp": "私は窓枠に手をかける。",
      "cn": "",
      "type": "narration",
      "translations": {
        "v1": "",
        "v2": "",
        "v3": "",
        "final": ""
      },
      "verified": false,
      "context": {
        "before": "遠野　紗夜「ええ」",
        "after": "日生　光「どうしたの？」"
      }
    },
    {
      "line": 58,
      "jp": "日生　光「どうしたの？」",
      "cn": "",
      "type": "dialogue",
      "translations": {
        "v1": "",
        "v2": "",
        "v3": "",
        "final": ""
      },
      "verified": false,
      "speaker": "日生　光",
      "special_char": true,
      "context": {
        "before": "私は窓枠に手をかける。",
        "after": "遠野　紗夜「ここから、どうやって帰ろうかと思って」"
      }
    },
    {
      "line": 59,
      "jp": "遠野　紗夜「ここから、どうやって帰ろうかと思って」",
      "cn": "",
      "type": "dialogue",
      "translations": {
        "v1": "",
        "v2": "",
        "v3": "",
        "final": ""
      },
      "verified": false,
      "speaker": "遠野　紗夜",
      "special_char": true,
      "context": {
        "before": "日生　光「どうしたの？」",
        "after": "日生　光「ここから？　ここ、二階だけど」"
      }
    },
    {
      "line": 60,
      "jp": "日生　光「ここから？　ここ、二階だけど」",
      "cn": "",
      "type": "dialogue",
      "translations": {
        "v1": "",
        "v2": "",
        "v3": "",
        "final": ""
      },
      "verified": false,
      "speaker": "日生　光",
      "special_char": true,
      "context": {
        "before": "遠野　紗夜「ここから、どうやって帰ろうかと思って」",
        "after": "遠野　紗夜「結構、高いですね……」"
      }
    },
    {
      "line": 61,
      "jp": "遠野　紗夜「結構、高いですね……」",
      "cn": "",
      "type": "dialogue",
      "translations": {
        "v1": "",
        "v2": "",
        "v3": "",
        "final": ""
      },
      "verified": false,
      "speaker": "遠野　紗夜",
      "special_char": true,
      "context": {
        "before": "日生　光「ここから？　ここ、二階だけど」",
        "after": "日生　光「当たり前だ。ここから飛び降りる気？」"
      }
    },
    {
      "line": 62,
      "jp": "日生　光「当たり前だ。ここから飛び降りる気？」",
      "cn": "",
      "type": "dialogue",
      "translations": {
        "v1": "",
        "v2": "",
        "v3": "",
        "final": ""
      },
      "verified": false,
      "speaker": "日生　光",
      "special_char": true,
      "context": {
        "before": "遠野　紗夜「結構、高いですね……」",
        "after": "遠野　紗夜「……塔の上のお姫様のようですね」"
      }
    },
    {
      "line": 63,
      "jp": "遠野　紗夜「……塔の上のお姫様のようですね」",
      "cn": "",
      "type": "dialogue",
      "translations": {
        "v1": "",
        "v2": "",
        "v3": "",
        "final": ""
      },
      "verified": false,
      "speaker": "遠野　紗夜",
      "special_char": true,
      "context": {
        "before": "日生　光「当たり前だ。ここから飛び降りる気？」",
        "after": "日生　光「お姫様？」"
      }
    },
    {
      "line": 64,
      "jp": "日生　光「お姫様？」",
      "cn": "",
      "type": "dialogue",
      "translations": {
        "v1": "",
        "v2": "",
        "v3": "",
        "final": ""
      },
      "verified": false,
      "speaker": "日生　光",
      "special_char": true,
      "context": {
        "before": "遠野　紗夜「……塔の上のお姫様のようですね」",
        "after": "遠野　紗夜「ええ。入り口のない高い高い塔の上に捕らわれたお姫様のお話です」"
      }
    },
    {
      "line": 65,
      "jp": "遠野　紗夜「ええ。入り口のない高い高い塔の上に捕らわれたお姫様のお話です」",
      "cn": "",
      "type": "dialogue",
      "translations": {
        "v1": "",
        "v2": "",
        "v3": "",
        "final": ""
      },
      "verified": false,
      "speaker": "遠野　紗夜",
      "special_char": true,
      "context": {
        "before": "日生　光「お姫様？」",
        "after": "日生　光「へえ」"
      }
    },
    {
      "line": 66,
      "jp": "日生　光「へえ」",
      "cn": "",
      "type": "dialogue",
      "translations": {
        "v1": "",
        "v2": "",
        "v3": "",
        "final": ""
      },
      "verified": false,
      "speaker": "日生　光",
      "special_char": true,
      "context": {
        "before": "遠野　紗夜「ええ。入り口のない高い高い塔の上に捕らわれたお姫様のお話です」",
        "after": "遠野　紗夜「お姫様は魔女に囚われていて、ずっと塔から抜け出したいのに抜け出せないのです」"
      }
    },
    {
      "line": 67,
      "jp": "遠野　紗夜「お姫様は魔女に囚われていて、ずっと塔から抜け出したいのに抜け出せないのです」",
      "cn": "",
      "type": "dialogue",
      "translations": {
        "v1": "",
        "v2": "",
        "v3": "",
        "final": ""
      },
      "verified": false,
      "speaker": "遠野　紗夜",
      "special_char": true,
      "context": {
        "before": "日生　光「へえ」",
        "after": "遠野　紗夜「ですが、ある時王子様が現れて、二人は魔女に秘密の逢瀬を繰り返す」"
      }
    },
    {
      "line": 68,
      "jp": "遠野　紗夜「ですが、ある時王子様が現れて、二人は魔女に秘密の逢瀬を繰り返す」",
      "cn": "",
      "type": "dialogue",
      "translations": {
        "v1": "",
        "v2": "",
        "v3": "",
        "final": ""
      },
      "verified": false,
      "speaker": "遠野　紗夜",
      "special_char": true,
      "context": {
        "before": "遠野　紗夜「お姫様は魔女に囚われていて、ずっと塔から抜け出したいのに抜け出せないのです」",
        "after": "私は口元にうっすらと笑みを称え、少々剣呑な目つきで日生先輩を見た。"
      }
    },
    {
      "line": 69,
      "jp": "私は口元にうっすらと笑みを称え、少々剣呑な目つきで日生先輩を見た。",
      "cn": "",
      "type": "narration",
      "translations": {
        "v1": "",
        "v2": "",
        "v3": "",
        "final": ""
      },
      "verified": false,
      "context": {
        "before": "遠野　紗夜「ですが、ある時王子様が現れて、二人は魔女に秘密の逢瀬を繰り返す」",
        "after": "彼は私の言いたいことがすぐに分かったようで、同じように口元に笑みを浮かべて言った。"
      }
    },
    {
      "line": 70,
      "jp": "彼は私の言いたいことがすぐに分かったようで、同じように口元に笑みを浮かべて言った。",
      "cn": "",
      "type": "narration",
      "translations": {
        "v1": "",
        "v2": "",
        "v3": "",
        "final": ""
      },
      "verified": false,
      "context": {
        "before": "私は口元にうっすらと笑みを称え、少々剣呑な目つきで日生先輩を見た。",
        "after": "日生　光「君は王子様？」"
      }
    },
    {
      "line": 71,
      "jp": "日生　光「君は王子様？」",
      "cn": "",
      "type": "dialogue",
      "translations": {
        "v1": "",
        "v2": "",
        "v3": "",
        "final": ""
      },
      "verified": false,
      "speaker": "日生　光",
      "special_char": true,
      "context": {
        "before": "彼は私の言いたいことがすぐに分かったようで、同じように口元に笑みを浮かべて言った。",
        "after": "遠野　紗夜「貴方はお姫様？」"
      }
    },
    {
      "line": 72,
      "jp": "遠野　紗夜「貴方はお姫様？」",
      "cn": "",
      "type": "dialogue",
      "translations": {
        "v1": "",
        "v2": "",
        "v3": "",
        "final": ""
      },
      "verified": false,
      "speaker": "遠野　紗夜",
      "special_char": true,
      "context": {
        "before": "日生　光「君は王子様？」",
        "after": "私達は秘やかに笑い合った。"
      }
    },
    {
      "line": 73,
      "jp": "私達は秘やかに笑い合った。",
      "cn": "",
      "type": "narration",
      "translations": {
        "v1": "",
        "v2": "",
        "v3": "",
        "final": ""
      },
      "verified": false,
      "context": {
        "before": "遠野　紗夜「貴方はお姫様？」",
        "after": null
      }
    }
  ]
}